HISTORY.md
MANIFEST.in
README.md
requirements.txt
setup.cfg
setup.py
pico/__init__.py
pico/conf.py
pico/context_processors.py
pico/menu.py
pico/settings.py
pico/urls.py
pico/views.py
pico/wsgi.py
pico/contact/__init__.py
pico/contact/admin.py
pico/contact/forms.py
pico/contact/models.py
pico/contact/urls.py
pico/contact/views.py
pico/contact/migrations/0001_initial.py
pico/contact/migrations/__init__.py
pico/contact/templates/contact/message_form.html
pico/contact/templates/default/contact/message_form.html
pico/contrib/apple/__init__.py
pico/contrib/apple/reviews.py
pico/miditags/__init__.py
pico/miditags/apps.py
pico/miditags/handlers.py
pico/miditags/helpers.py
pico/miditags/registry.py
pico/miditags/templatetags/__init__.py
pico/miditags/templatetags/miditags.py
pico/podcasts/__init__.py
pico/podcasts/admin.py
pico/podcasts/apps.py
pico/podcasts/middleware.py
pico/podcasts/miditags.py
pico/podcasts/models.py
pico/podcasts/query.py
pico/podcasts/search.py
pico/podcasts/tasks.py
pico/podcasts/urls.py
pico/podcasts/utils.py
pico/podcasts/views.py
pico/podcasts/management/__init__.py
pico/podcasts/management/commands/__init__.py
pico/podcasts/management/commands/addfeed.py
pico/podcasts/management/commands/checkfeeds.py
pico/podcasts/management/commands/checkreviews.py
pico/podcasts/migrations/0001_initial.py
pico/podcasts/migrations/0002_alter_podcast_domain.py
pico/podcasts/migrations/0003_podcast_short_name.py
pico/podcasts/migrations/0004_auto_20210922_1631.py
pico/podcasts/migrations/0005_podcast_about_page.py
pico/podcasts/migrations/0006_auto_20211210_1207.py
pico/podcasts/migrations/0007_podcast_ordering.py
pico/podcasts/migrations/0008_podcast_subscription.py
pico/podcasts/migrations/0009_auto_20220213_1407.py
pico/podcasts/migrations/0010_review.py
pico/podcasts/migrations/0011_podcast_head_html.py
pico/podcasts/migrations/0012_rename_ordering_podcast_episode_ordering.py
pico/podcasts/migrations/0013_podcast_contact_form.py
pico_podcast.egg-info/PKG-INFO
pico_podcast.egg-info/SOURCES.txt
pico_podcast.egg-info/dependency_links.txt
pico_podcast.egg-info/not-zip-safe
pico_podcast.egg-info/requires.txt
pico_podcast.egg-info/top_level.txt