Metadata-Version: 2.1
Name: pico-podcast
Version: 0.20.0
Summary: Simple podcast websites, powered by Django.
Home-page: https://git.steadman.io/origin/pico
Author: Mark Steadman
Author-email: mark@origin.fm
License: MIT
Keywords: pico-podcast
Classifier: Development Status :: 3 - Alpha
Classifier: Framework :: Django :: 2.1
Classifier: Intended Audience :: Developers
Classifier: License :: OSI Approved :: BSD License
Classifier: Natural Language :: English
Classifier: Programming Language :: Python :: 2
Classifier: Programming Language :: Python :: 2.7
Classifier: Programming Language :: Python :: 3
Classifier: Programming Language :: Python :: 3.5
Classifier: Programming Language :: Python :: 3.6
